{"name":"build-javascript","namedChunkGroups":{"polyfill":{"name":"polyfill","assets":[{"name":"webpack-runtime-67ccf019f752c4f0c106.js","size":5714},{"name":"polyfill-c90fcfe287385df964e1.js","size":85876}],"filteredAssets":0,"assetsSize":91590,"filteredAuxiliaryAssets":2,"auxiliaryAssetsSize":229526},"app":{"name":"app","assets":[{"name":"webpack-runtime-67ccf019f752c4f0c106.js","size":5714},{"name":"framework-0527f076d8e94914060e.js","size":150871},{"name":"app-aa7f5cf93b02b7e13ca6.js","size":266424}],"filteredAssets":0,"assetsSize":423009,"filteredAuxiliaryAssets":24,"auxiliaryAssetsSize":4751845},"component---src-components-page-templates-blog-page-tsx":{"name":"component---src-components-page-templates-blog-page-tsx","assets":[{"name":"styles.4ff0ace326836caa8308.css","size":207490},{"name":"framework-0527f076d8e94914060e.js","size":150871},{"name":"37bf9728-0c244e9182f8fcdfea0d.js","size":455254},{"name":"82c1d43a-bf6112bc7bb2d9977244.js","size":340987},{"name":"0f86a987-56971398f32314a33ff1.js","size":163368},{"name":"commons-af70eebb489ca0464a20.js","size":92629},{"name":"5362dffe27923e249f40e4ba698d14ab4771a0f9-48b5ef0a29760870e449.js","size":244115},{"name":"99f28a3450395f2941534da4854146b600be20a6-4e56fa662a59f2113f3f.js","size":21686},{"name":"component---src-components-page-templates-blog-page-tsx-3828b45808966add106c.js","size":3128}],"filteredAssets":0,"assetsSize":1679528,"filteredAuxiliaryAssets":20,"auxiliaryAssetsSize":4345260},"component---src-components-page-templates-info-page-tsx":{"name":"component---src-components-page-templates-info-page-tsx","assets":[{"name":"styles.4ff0ace326836caa8308.css","size":207490},{"name":"framework-0527f076d8e94914060e.js","size":150871},{"name":"37bf9728-0c244e9182f8fcdfea0d.js","size":455254},{"name":"82c1d43a-bf6112bc7bb2d9977244.js","size":340987},{"name":"0f86a987-56971398f32314a33ff1.js","size":163368},{"name":"commons-af70eebb489ca0464a20.js","size":92629},{"name":"5362dffe27923e249f40e4ba698d14ab4771a0f9-48b5ef0a29760870e449.js","size":244115},{"name":"component---src-components-page-templates-info-page-tsx-beb253356bc8bdf769aa.js","size":772}],"filteredAssets":0,"assetsSize":1655486,"filteredAuxiliaryAssets":19,"auxiliaryAssetsSize":4216022},"component---src-pages-404-tsx":{"name":"component---src-pages-404-tsx","assets":[{"name":"styles.4ff0ace326836caa8308.css","size":207490},{"name":"framework-0527f076d8e94914060e.js","size":150871},{"name":"37bf9728-0c244e9182f8fcdfea0d.js","size":455254},{"name":"82c1d43a-bf6112bc7bb2d9977244.js","size":340987},{"name":"0f86a987-56971398f32314a33ff1.js","size":163368},{"name":"commons-af70eebb489ca0464a20.js","size":92629},{"name":"5362dffe27923e249f40e4ba698d14ab4771a0f9-48b5ef0a29760870e449.js","size":244115},{"name":"component---src-pages-404-tsx-751e77668e9ae3676c38.js","size":465}],"filteredAssets":0,"assetsSize":1655179,"filteredAuxiliaryAssets":19,"auxiliaryAssetsSize":4213967},"component---src-pages-blog-tsx":{"name":"component---src-pages-blog-tsx","assets":[{"name":"styles.4ff0ace326836caa8308.css","size":207490},{"name":"commons-af70eebb489ca0464a20.js","size":92629},{"name":"99f28a3450395f2941534da4854146b600be20a6-4e56fa662a59f2113f3f.js","size":21686},{"name":"component---src-pages-blog-tsx-567acc5c2232282af18b.js","size":1047}],"filteredAssets":0,"assetsSize":322852,"filteredAuxiliaryAssets":15,"auxiliaryAssetsSize":696321},"component---src-pages-contact-tsx":{"name":"component---src-pages-contact-tsx","assets":[{"name":"styles.4ff0ace326836caa8308.css","size":207490},{"name":"framework-0527f076d8e94914060e.js","size":150871},{"name":"37bf9728-0c244e9182f8fcdfea0d.js","size":455254},{"name":"82c1d43a-bf6112bc7bb2d9977244.js","size":340987},{"name":"0f86a987-56971398f32314a33ff1.js","size":163368},{"name":"commons-af70eebb489ca0464a20.js","size":92629},{"name":"5362dffe27923e249f40e4ba698d14ab4771a0f9-48b5ef0a29760870e449.js","size":244115},{"name":"component---src-pages-contact-tsx-9416a717ce6d1d29d702.js","size":571}],"filteredAssets":0,"assetsSize":1655285,"filteredAuxiliaryAssets":19,"auxiliaryAssetsSize":4214338},"component---src-pages-index-tsx":{"name":"component---src-pages-index-tsx","assets":[{"name":"styles.4ff0ace326836caa8308.css","size":207490},{"name":"framework-0527f076d8e94914060e.js","size":150871},{"name":"37bf9728-0c244e9182f8fcdfea0d.js","size":455254},{"name":"82c1d43a-bf6112bc7bb2d9977244.js","size":340987},{"name":"0f86a987-56971398f32314a33ff1.js","size":163368},{"name":"commons-af70eebb489ca0464a20.js","size":92629},{"name":"5362dffe27923e249f40e4ba698d14ab4771a0f9-48b5ef0a29760870e449.js","size":244115},{"name":"component---src-pages-index-tsx-44d1d6719fca3acdfca5.js","size":568}],"filteredAssets":0,"assetsSize":1655282,"filteredAuxiliaryAssets":19,"auxiliaryAssetsSize":4214349}},"assetsByChunkName":{"polyfill":["webpack-runtime-67ccf019f752c4f0c106.js","polyfill-c90fcfe287385df964e1.js"],"app":["webpack-runtime-67ccf019f752c4f0c106.js","framework-0527f076d8e94914060e.js","app-aa7f5cf93b02b7e13ca6.js"],"component---src-components-page-templates-blog-page-tsx":["styles.4ff0ace326836caa8308.css","framework-0527f076d8e94914060e.js","37bf9728-0c244e9182f8fcdfea0d.js","82c1d43a-bf6112bc7bb2d9977244.js","0f86a987-56971398f32314a33ff1.js","commons-af70eebb489ca0464a20.js","5362dffe27923e249f40e4ba698d14ab4771a0f9-48b5ef0a29760870e449.js","99f28a3450395f2941534da4854146b600be20a6-4e56fa662a59f2113f3f.js","component---src-components-page-templates-blog-page-tsx-3828b45808966add106c.js"],"component---src-components-page-templates-info-page-tsx":["styles.4ff0ace326836caa8308.css","framework-0527f076d8e94914060e.js","37bf9728-0c244e9182f8fcdfea0d.js","82c1d43a-bf6112bc7bb2d9977244.js","0f86a987-56971398f32314a33ff1.js","commons-af70eebb489ca0464a20.js","5362dffe27923e249f40e4ba698d14ab4771a0f9-48b5ef0a29760870e449.js","component---src-components-page-templates-info-page-tsx-beb253356bc8bdf769aa.js"],"component---src-pages-404-tsx":["styles.4ff0ace326836caa8308.css","framework-0527f076d8e94914060e.js","37bf9728-0c244e9182f8fcdfea0d.js","82c1d43a-bf6112bc7bb2d9977244.js","0f86a987-56971398f32314a33ff1.js","commons-af70eebb489ca0464a20.js","5362dffe27923e249f40e4ba698d14ab4771a0f9-48b5ef0a29760870e449.js","component---src-pages-404-tsx-751e77668e9ae3676c38.js"],"component---src-pages-blog-tsx":["styles.4ff0ace326836caa8308.css","commons-af70eebb489ca0464a20.js","99f28a3450395f2941534da4854146b600be20a6-4e56fa662a59f2113f3f.js","component---src-pages-blog-tsx-567acc5c2232282af18b.js"],"component---src-pages-contact-tsx":["styles.4ff0ace326836caa8308.css","framework-0527f076d8e94914060e.js","37bf9728-0c244e9182f8fcdfea0d.js","82c1d43a-bf6112bc7bb2d9977244.js","0f86a987-56971398f32314a33ff1.js","commons-af70eebb489ca0464a20.js","5362dffe27923e249f40e4ba698d14ab4771a0f9-48b5ef0a29760870e449.js","component---src-pages-contact-tsx-9416a717ce6d1d29d702.js"],"component---src-pages-index-tsx":["styles.4ff0ace326836caa8308.css","framework-0527f076d8e94914060e.js","37bf9728-0c244e9182f8fcdfea0d.js","82c1d43a-bf6112bc7bb2d9977244.js","0f86a987-56971398f32314a33ff1.js","commons-af70eebb489ca0464a20.js","5362dffe27923e249f40e4ba698d14ab4771a0f9-48b5ef0a29760870e449.js","component---src-pages-index-tsx-44d1d6719fca3acdfca5.js"]},"childAssetsByChunkName":{}}